{
  "nhits": 131,
  "parameters": {
    "dataset": "referentiel-gares-voyageurs",
    "timezone": "UTC",
    "q": "gare_regionsncf_libelle=\"REGION LORRAINE\"",
    "rows": 10,
    "start": 0,
    "sort": [
      "gare_alias_libelle_noncontraint"
    ],
    "format": "json"
  },
  "records": [
    {
      "datasetid": "referentiel-gares-voyageurs",
      "recordid": "cf127c79c8f89d6042f6a7b3533a083e31ccd075",
      "fields": {
        "code": "02708-1",
        "departement_numero": "57",
        "departement_libellemin": "Moselle",
        "gare": "{\"DRG_ON\": true, \"Etrangere_ON\": false, \"NbPltf\": 1, \"Alias_Libelle_NonContraint\": \"Ancy-sur-Moselle\", \"Alias_Libelle_Fronton\": \"Ancy-sur-Moselle\", \"AgenceGC_Libelle\": \"DTG Grand Est\", \"RegionSNCF_Libelle\": \"REGION LORRAINE\", \"UG_Libelle\": \"UG Lorraine\", \"UT_Libelle\": \"ANCY SUR MOSELLE GARE\"}",
        "gare_ut_libelle": "ANCY SUR MOSELLE GARE",
        "tvs": "AYM",
        "tvss": "[{\"TVS_Code\": \"AYM\"}]",
        "uic_code": "0087192419",
        "gare_alias_libelle_noncontraint": "Ancy-sur-Moselle",
        "longitude_entreeprincipale_wgs84": "6.0627661",
        "wgs_84": [
          49.0575093,
          6.0627661
        ],
        "segmentdrg_libelle": "c",
        "gare_etrangere_on": "False",
        "niveauservice_libelle": 1,
        "commune_code": "021",
        "gare_drg_on": "True",
        "gare_agencegc_libelle": "DTG Grand Est",
        "gare_regionsncf_libelle": "REGION LORRAINE",
        "commune_libellemin": "Ancy-Dornot",
        "gare_alias_libelle_fronton": "Ancy-sur-Moselle",
        "alias_libelle_noncontraint": "Ancy-sur-Moselle",
        "adresse_cp": "57130",
        "gare_ug_libelle": "UG Lorraine",
        "latitude_entreeprincipale_wgs84": "49.0575093",
        "rg_libelle": "GARES C LORRAINE",
        "gare_nbpltf": 1
      },
      "geometry": {
        "type": "Point",
        "coordinates": [
          6.0627661,
          49.0575093
        ]
      },
      "record_timestamp": "2021-03-16T23:00:20.305000+00:00"
    },
    {
      "datasetid": "referentiel-gares-voyageurs",
      "recordid": "f3a170547900e7b17b5dbd5ec856fb70888f174e",
      "fields": {
        "code": "02725-1",
        "departement_numero": "57",
        "departement_libellemin": "Moselle",
        "gare": "{\"DRG_ON\": true, \"Etrangere_ON\": false, \"NbPltf\": 1, \"Alias_Libelle_NonContraint\": \"Apach\", \"Alias_Libelle_Fronton\": \"Apach\", \"AgenceGC_Libelle\": \"DTG Grand Est\", \"RegionSNCF_Libelle\": \"REGION LORRAINE\", \"UG_Libelle\": \"UG Lorraine\", \"UT_Libelle\": \"APACH (MOSELLE) GARE\"}",
        "gare_ut_libelle": "APACH (MOSELLE) GARE",
        "tvs": "APJ",
        "tvss": "[{\"TVS_Code\": \"APJ\"}]",
        "uic_code": "0087191643",
        "gare_alias_libelle_noncontraint": "Apach",
        "longitude_entreeprincipale_wgs84": "6.371972",
        "wgs_84": [
          49.458836,
          6.371972
        ],
        "segmentdrg_libelle": "c",
        "gare_etrangere_on": "False",
        "niveauservice_libelle": 1,
        "commune_code": "026",
        "gare_drg_on": "True",
        "gare_agencegc_libelle": "DTG Grand Est",
        "gare_regionsncf_libelle": "REGION LORRAINE",
        "commune_libellemin": "Apach",
        "gare_alias_libelle_fronton": "Apach",
        "alias_libelle_noncontraint": "Apach",
        "adresse_cp": "57480",
        "gare_ug_libelle": "UG Lorraine",
        "latitude_entreeprincipale_wgs84": "49.458836",
        "rg_libelle": "GARES C LORRAINE",
        "gare_nbpltf": 1
      },
      "geometry": {
        "type": "Point",
        "coordinates": [
          6.371972,
          49.458836
        ]
      },
      "record_timestamp": "2021-03-16T23:00:20.305000+00:00"
    },
    {
      "datasetid": "referentiel-gares-voyageurs",
      "recordid": "2b17bed46d083ab3a25bdddbf26be27a779ffef4",
      "fields": {
        "code": "02918-1",
        "departement_numero": "88",
        "departement_libellemin": "Vosges",
        "gare": "{\"DRG_ON\": true, \"Etrangere_ON\": false, \"NbPltf\": 1, \"Alias_Libelle_NonContraint\": \"Arches\", \"Alias_Libelle_Fronton\": \"Arches\", \"AgenceGC_Libelle\": \"DTG Grand Est\", \"RegionSNCF_Libelle\": \"REGION LORRAINE\", \"UG_Libelle\": \"UG Lorraine\", \"UT_Libelle\": \"ARCHES GARE\"}",
        "gare_ut_libelle": "ARCHES GARE",
        "tvs": "ARH",
        "tvss": "[{\"TVS_Code\": \"ARH\"}]",
        "uic_code": "0087144410",
        "gare_alias_libelle_noncontraint": "Arches",
        "longitude_entreeprincipale_wgs84": "6.5283085",
        "wgs_84": [
          48.1198133,
          6.5283085
        ],
        "segmentdrg_libelle": "c",
        "gare_etrangere_on": "False",
        "niveauservice_libelle": 1,
        "commune_code": "011",
        "gare_drg_on": "True",
        "gare_agencegc_libelle": "DTG Grand Est",
        "gare_regionsncf_libelle": "REGION LORRAINE",
        "commune_libellemin": "Arches",
        "gare_alias_libelle_fronton": "Arches",
        "alias_libelle_noncontraint": "Arches",
        "adresse_cp": "88380",
        "gare_ug_libelle": "UG Lorraine",
        "latitude_entreeprincipale_wgs84": "48.1198133",
        "rg_libelle": "GARES C LORRAINE",
        "gare_nbpltf": 1
      },
      "geometry": {
        "type": "Point",
        "coordinates": [
          6.5283085,
          48.1198133
        ]
      },
      "record_timestamp": "2021-03-16T23:00:20.305000+00:00"
    },
    {
      "datasetid": "referentiel-gares-voyageurs",
      "recordid": "28ad090b5fc00fb35fc7283ff341639589fca485",
      "fields": {
        "code": "02709-1",
        "departement_numero": "57",
        "departement_libellemin": "Moselle",
        "gare": "{\"DRG_ON\": true, \"Etrangere_ON\": false, \"NbPltf\": 1, \"Alias_Libelle_NonContraint\": \"Ars-sur-Moselle\", \"Alias_Libelle_Fronton\": \"Ars-sur-Moselle\", \"AgenceGC_Libelle\": \"DTG Grand Est\", \"RegionSNCF_Libelle\": \"REGION LORRAINE\", \"UG_Libelle\": \"UG Lorraine\", \"UT_Libelle\": \"ARS SUR MOSELLE GARE\"}",
        "gare_ut_libelle": "ARS SUR MOSELLE GARE",
        "tvs": "ASM",
        "tvss": "[{\"TVS_Code\": \"ASM\"}]",
        "uic_code": "0087192401",
        "gare_alias_libelle_noncontraint": "Ars-sur-Moselle",
        "longitude_entreeprincipale_wgs84": "6.0776461",
        "wgs_84": [
          49.0744745,
          6.0776461
        ],
        "segmentdrg_libelle": "b",
        "gare_etrangere_on": "False",
        "niveauservice_libelle": 1,
        "commune_code": "032",
        "gare_drg_on": "True",
        "gare_agencegc_libelle": "DTG Grand Est",
        "gare_regionsncf_libelle": "REGION LORRAINE",
        "commune_libellemin": "Ars-sur-Moselle",
        "gare_alias_libelle_fronton": "Ars-sur-Moselle",
        "alias_libelle_noncontraint": "Ars-sur-Moselle",
        "adresse_cp": "57130",
        "gare_ug_libelle": "UG Lorraine",
        "latitude_entreeprincipale_wgs84": "49.0744745",
        "rg_libelle": "GARES B LORRAINE",
        "gare_nbpltf": 1
      },
      "geometry": {
        "type": "Point",
        "coordinates": [
          6.0776461,
          49.0744745
        ]
      },
      "record_timestamp": "2021-03-16T23:00:20.305000+00:00"
    },
    {
      "datasetid": "referentiel-gares-voyageurs",
      "recordid": "a1336c689cef3114866063c2211f5eb08e72eca2",
      "fields": {
        "code": "02724-1",
        "departement_numero": "54",
        "departement_libellemin": "Meurthe-et-Moselle",
        "gare": "{\"DRG_ON\": true, \"Etrangere_ON\": false, \"NbPltf\": 1, \"Alias_Libelle_NonContraint\": \"Aubou\u00e9\", \"Alias_Libelle_Fronton\": \"Aubou\u00e9\", \"AgenceGC_Libelle\": \"DTG Grand Est\", \"RegionSNCF_Libelle\": \"REGION LORRAINE\", \"UG_Libelle\": \"UG Lorraine\", \"UT_Libelle\": \"AUBOUE P GARE\"}",
        "gare_ut_libelle": "AUBOUE P GARE",
        "tvs": "ABE",
        "tvss": "[{\"TVS_Code\": \"ABE\"}]",
        "uic_code": "0087191684",
        "gare_alias_libelle_noncontraint": "Aubou\u00e9",
        "longitude_entreeprincipale_wgs84": "5.9714608",
        "wgs_84": [
          49.216163,
          5.9714608
        ],
        "segmentdrg_libelle": "c",
        "gare_etrangere_on": "False",
        "niveauservice_libelle": 1,
        "commune_code": "028",
        "gare_drg_on": "True",
        "gare_agencegc_libelle": "DTG Grand Est",
        "gare_regionsncf_libelle": "REGION LORRAINE",
        "commune_libellemin": "Aubou\u00e9",
        "gare_alias_libelle_fronton": "Aubou\u00e9",
        "alias_libelle_noncontraint": "Aubou\u00e9",
        "adresse_cp": "54580",
        "gare_ug_libelle": "UG Lorraine",
        "latitude_entreeprincipale_wgs84": "49.216163",
        "rg_libelle": "GARES C LORRAINE",
        "gare_nbpltf": 1
      },
      "geometry": {
        "type": "Point",
        "coordinates": [
          5.9714608,
          49.216163
        ]
      },
      "record_timestamp": "2021-03-16T23:00:20.305000+00:00"
    },
    {
      "datasetid": "referentiel-gares-voyageurs",
      "recordid": "fee5ba26fd53c4c23d4e435de1b1fb55a8e26ea5",
      "fields": {
        "code": "02671-1",
        "departement_numero": "54",
        "departement_libellemin": "Meurthe-et-Moselle",
        "gare": "{\"DRG_ON\": true, \"Etrangere_ON\": false, \"NbPltf\": 1, \"Alias_Libelle_NonContraint\": \"Audun-le-Roman\", \"Alias_Libelle_Fronton\": \"Audun-le-Roman\", \"AgenceGC_Libelle\": \"DTG Grand Est\", \"RegionSNCF_Libelle\": \"REGION LORRAINE\", \"UG_Libelle\": \"UG Lorraine\", \"UT_Libelle\": \"AUDUN LE ROMAN GARE\"}",
        "gare_ut_libelle": "AUDUN LE ROMAN GARE",
        "tvs": "ALR",
        "tvss": "[{\"TVS_Code\": \"ALR\"}]",
        "uic_code": "0087194357",
        "gare_alias_libelle_noncontraint": "Audun-le-Roman",
        "longitude_entreeprincipale_wgs84": "5.89139",
        "wgs_84": [
          49.36682,
          5.89139
        ],
        "segmentdrg_libelle": "c",
        "gare_etrangere_on": "False",
        "niveauservice_libelle": 1,
        "commune_code": "029",
        "gare_drg_on": "True",
        "gare_agencegc_libelle": "DTG Grand Est",
        "gare_regionsncf_libelle": "REGION LORRAINE",
        "commune_libellemin": "Audun-le-Roman",
        "gare_alias_libelle_fronton": "Audun-le-Roman",
        "alias_libelle_noncontraint": "Audun-le-Roman",
        "adresse_cp": "54560",
        "gare_ug_libelle": "UG Lorraine",
        "latitude_entreeprincipale_wgs84": "49.36682",
        "rg_libelle": "GARES C LORRAINE",
        "gare_nbpltf": 1
      },
      "geometry": {
        "type": "Point",
        "coordinates": [
          5.89139,
          49.36682
        ]
      },
      "record_timestamp": "2021-03-16T23:00:20.305000+00:00"
    },
    {
      "datasetid": "referentiel-gares-voyageurs",
      "recordid": "91c09c3ce9115ac092608e2b831d6ffcbc207ed1",
      "fields": {
        "code": "02981-1",
        "departement_numero": "54",
        "departement_libellemin": "Meurthe-et-Moselle",
        "gare": "{\"DRG_ON\": true, \"Etrangere_ON\": false, \"NbPltf\": 1, \"Alias_Libelle_NonContraint\": \"Azerailles\", \"Alias_Libelle_Fronton\": \"Azerailles\", \"AgenceGC_Libelle\": \"DTG Grand Est\", \"RegionSNCF_Libelle\": \"REGION LORRAINE\", \"UG_Libelle\": \"UG Lorraine\", \"UT_Libelle\": \"AZERAILLES GARE\"}",
        "gare_ut_libelle": "AZERAILLES GARE",
        "tvs": "AZE",
        "tvss": "[{\"TVS_Code\": \"AZE\"}]",
        "uic_code": "0087141408",
        "gare_alias_libelle_noncontraint": "Azerailles",
        "longitude_entreeprincipale_wgs84": "6.695778",
        "wgs_84": [
          48.4913355,
          6.695778
        ],
        "segmentdrg_libelle": "c",
        "gare_etrangere_on": "False",
        "niveauservice_libelle": 1,
        "commune_code": "038",
        "gare_drg_on": "True",
        "gare_agencegc_libelle": "DTG Grand Est",
        "gare_regionsncf_libelle": "REGION LORRAINE",
        "commune_libellemin": "Azerailles",
        "gare_alias_libelle_fronton": "Azerailles",
        "alias_libelle_noncontraint": "Azerailles",
        "adresse_cp": "54122",
        "gare_ug_libelle": "UG Lorraine",
        "latitude_entreeprincipale_wgs84": "48.4913355",
        "rg_libelle": "GARES C LORRAINE",
        "gare_nbpltf": 1
      },
      "geometry": {
        "type": "Point",
        "coordinates": [
          6.695778,
          48.4913355
        ]
      },
      "record_timestamp": "2021-03-16T23:00:20.305000+00:00"
    },
    {
      "datasetid": "referentiel-gares-voyageurs",
      "recordid": "3b0488a661f46f9c8eb78e5e56f272d7257d9f1c",
      "fields": {
        "code": "02980-1",
        "departement_numero": "54",
        "departement_libellemin": "Meurthe-et-Moselle",
        "gare": "{\"DRG_ON\": true, \"Etrangere_ON\": false, \"NbPltf\": 1, \"Alias_Libelle_NonContraint\": \"Baccarat\", \"Alias_Libelle_Fronton\": \"Baccarat\", \"AgenceGC_Libelle\": \"DTG Grand Est\", \"RegionSNCF_Libelle\": \"REGION LORRAINE\", \"UG_Libelle\": \"UG Lorraine\", \"UT_Libelle\": \"BACCARAT GARE\"}",
        "gare_ut_libelle": "BACCARAT GARE",
        "tvs": "BAC",
        "tvss": "[{\"TVS_Code\": \"BAC\"}]",
        "uic_code": "0087141416",
        "gare_alias_libelle_noncontraint": "Baccarat",
        "longitude_entreeprincipale_wgs84": "6.743830",
        "wgs_84": [
          48.452405,
          6.74383
        ],
        "segmentdrg_libelle": "b",
        "gare_etrangere_on": "False",
        "niveauservice_libelle": 1,
        "commune_code": "039",
        "gare_drg_on": "True",
        "gare_agencegc_libelle": "DTG Grand Est",
        "gare_regionsncf_libelle": "REGION LORRAINE",
        "commune_libellemin": "Baccarat",
        "gare_alias_libelle_fronton": "Baccarat",
        "alias_libelle_noncontraint": "Baccarat",
        "adresse_cp": "54120",
        "gare_ug_libelle": "UG Lorraine",
        "latitude_entreeprincipale_wgs84": "48.452405",
        "rg_libelle": "GARES B LORRAINE",
        "gare_nbpltf": 1
      },
      "geometry": {
        "type": "Point",
        "coordinates": [
          6.74383,
          48.452405
        ]
      },
      "record_timestamp": "2021-03-16T23:00:20.305000+00:00"
    },
    {
      "datasetid": "referentiel-gares-voyageurs",
      "recordid": "623748306000e5049912edb0686f1a30685a143f",
      "fields": {
        "code": "02934-1",
        "departement_numero": "88",
        "departement_libellemin": "Vosges",
        "gare": "{\"DRG_ON\": true, \"Etrangere_ON\": false, \"NbPltf\": 1, \"Alias_Libelle_NonContraint\": \"Bains-les-Bains\", \"Alias_Libelle_Fronton\": \"Bains-les-Bains\", \"AgenceGC_Libelle\": \"DTG Grand Est\", \"RegionSNCF_Libelle\": \"REGION LORRAINE\", \"UG_Libelle\": \"UG Lorraine\", \"UT_Libelle\": \"BAINS LES BAINS GARE\"}",
        "gare_ut_libelle": "BAINS LES BAINS GARE",
        "tvs": "BNS",
        "tvss": "[{\"TVS_Code\": \"BNS\"}]",
        "uic_code": "0087144147",
        "gare_alias_libelle_noncontraint": "Bains-les-Bains",
        "longitude_entreeprincipale_wgs84": "6.2952683",
        "wgs_84": [
          47.9811282,
          6.2952683
        ],
        "segmentdrg_libelle": "c",
        "gare_etrangere_on": "False",
        "niveauservice_libelle": 1,
        "commune_code": "029",
        "gare_drg_on": "True",
        "gare_agencegc_libelle": "DTG Grand Est",
        "gare_regionsncf_libelle": "REGION LORRAINE",
        "commune_libellemin": "V\u00f4ge-les-Bains",
        "gare_alias_libelle_fronton": "Bains-les-Bains",
        "alias_libelle_noncontraint": "Bains-les-Bains",
        "adresse_cp": "88240",
        "gare_ug_libelle": "UG Lorraine",
        "latitude_entreeprincipale_wgs84": "47.9811282",
        "rg_libelle": "GARES C LORRAINE",
        "gare_nbpltf": 1
      },
      "geometry": {
        "type": "Point",
        "coordinates": [
          6.2952683,
          47.9811282
        ]
      },
      "record_timestamp": "2021-03-16T23:00:20.305000+00:00"
    },
    {
      "datasetid": "referentiel-gares-voyageurs",
      "recordid": "305842a69ad6782951a1ce0d6b9819abff6b18ab",
      "fields": {
        "code": "02838-1",
        "departement_numero": "55",
        "departement_libellemin": "Meuse",
        "gare": "{\"DRG_ON\": true, \"Etrangere_ON\": false, \"NbPltf\": 1, \"Alias_Libelle_NonContraint\": \"Bar-le-Duc\", \"Alias_Libelle_Fronton\": \"Bar-le-Duc\", \"AgenceGC_Libelle\": \"DTG Grand Est\", \"RegionSNCF_Libelle\": \"REGION LORRAINE\", \"UG_Libelle\": \"UG Lorraine\", \"UT_Libelle\": \"BAR LE DUC GARE\"}",
        "gare_ut_libelle": "BAR LE DUC GARE",
        "tvs": "BLD",
        "tvss": "[{\"TVS_Code\": \"BLD\"}]",
        "uic_code": "0087175042",
        "gare_alias_libelle_noncontraint": "Bar-le-Duc",
        "longitude_entreeprincipale_wgs84": "5.166822",
        "wgs_84": [
          48.773308,
          5.166822
        ],
        "segmentdrg_libelle": "b",
        "gare_etrangere_on": "False",
        "niveauservice_libelle": 2,
        "commune_code": "029",
        "gare_drg_on": "True",
        "gare_agencegc_libelle": "DTG Grand Est",
        "gare_regionsncf_libelle": "REGION LORRAINE",
        "commune_libellemin": "Bar-le-Duc",
        "gare_alias_libelle_fronton": "Bar-le-Duc",
        "alias_libelle_noncontraint": "Bar-le-Duc",
        "adresse_cp": "55000",
        "gare_ug_libelle": "UG Lorraine",
        "latitude_entreeprincipale_wgs84": "48.773308",
        "rg_libelle": "GARES B LORRAINE",
        "gare_nbpltf": 1
      },
      "geometry": {
        "type": "Point",
        "coordinates": [
          5.166822,
          48.773308
        ]
      },
      "record_timestamp": "2021-03-16T23:00:20.305000+00:00"
    }
  ]
}